LICENSE
MANIFEST.in
README.rst
setup.cfg
setup.py
django_question.egg-info/PKG-INFO
django_question.egg-info/SOURCES.txt
django_question.egg-info/dependency_links.txt
django_question.egg-info/top_level.txt
question/__init__.py
question/models.py
question/urls.py
question/api/__init__.py
question/api/apps.py
question/api/filters.py
question/api/mixins.py
question/api/permissions.py
question/api/serializers.py
question/api/tests.py
question/api/urls.py
question/api/views.py
question/cards/__init__.py
question/cards/admin.py
question/cards/apps.py
question/cards/models.py
question/cards/urls.py
question/cards/views.py
question/cards/migrations/__init__.py
question/comments/__init__.py
question/comments/admin.py
question/comments/apps.py
question/comments/models.py
question/comments/migrations/__init__.py
question/likes/__init__.py
question/likes/apps.py
question/likes/models.py
question/likes/migrations/__init__.py
question/nyssance/__init__.py
question/nyssance/cloudfile/__init__.py
question/nyssance/cloudfile/fields.py
question/nyssance/cloudfile/widgets.py
question/nyssance/django/__init__.py
question/nyssance/django/contrib/__init__.py
question/nyssance/django/contrib/admin.py
question/nyssance/django/db/__init__.py
question/nyssance/django/db/middleware.py
question/nyssance/django/db/models.py
question/nyssance/django/db/utils.py
question/nyssance/django/utils/__init__.py
question/nyssance/django/utils/apps.py
question/nyssance/rest_framework/__init__.py
question/nyssance/rest_framework/mixins.py
question/nyssance/rest_framework/pagination.py
question/nyssance/rest_framework/parsers.py
question/nyssance/rest_framework/permissions.py
question/nyssance/rest_framework/renderers.py
question/nyssance/rest_framework/response.py
question/nyssance/rest_framework/serializers.py
question/nyssance/rest_framework/views.py
question/nyssance/rest_framework_jwt/__init__.py
question/nyssance/rest_framework_jwt/utils.py
question/nyssance/utils/__init__.py
question/nyssance/utils/active_code.py
question/nyssance/utils/check_id_card.py
question/nyssance/utils/func_ext.py
question/nyssance/utils/py_mysql.py
